dp_accounting/__init__.py
dp_accounting/dp_event.py
dp_accounting/dp_event_builder.py
dp_accounting/dp_event_builder_test.py
dp_accounting/dp_event_test.py
dp_accounting/mechanism_calibration.py
dp_accounting/mechanism_calibration_test.py
dp_accounting/privacy_accountant.py
dp_accounting/privacy_accountant_test.py
dp_accounting/pld/__init__.py
dp_accounting/pld/accountant.py
dp_accounting/pld/accountant_test.py
dp_accounting/pld/common.py
dp_accounting/pld/common_test.py
dp_accounting/pld/pld_pmf.py
dp_accounting/pld/pld_pmf_test.py
dp_accounting/pld/pld_privacy_accountant.py
dp_accounting/pld/pld_privacy_accountant_test.py
dp_accounting/pld/privacy_loss_distribution.py
dp_accounting/pld/privacy_loss_distribution_basic_example.py
dp_accounting/pld/privacy_loss_distribution_test.py
dp_accounting/pld/privacy_loss_mechanism.py
dp_accounting/pld/privacy_loss_mechanism_test.py
dp_accounting/pld/test_util.py
dp_accounting/pld/test_util_test.py
dp_accounting/rdp/__init__.py
dp_accounting/rdp/rdp_privacy_accountant.py
dp_accounting/rdp/rdp_privacy_accountant_test.py
dp_accounting-0.5.1.dist-info/METADATA
dp_accounting-0.5.1.dist-info/WHEEL
dp_accounting-0.5.1.dist-info/top_level.txt
dp_accounting-0.5.1.dist-info/RECORD
