Metadata-Version: 2.4
Name: dp-accounting
Version: 0.5.1
Summary: Tools for tracking differential privacy budgets
Home-page: https://github.com/google/differential-privacy/
Author: Google Differential Privacy Team
Author-email: dp-open-source@google.com
License: Apache 2.0
Keywords: differential-privacy accounting
Classifier: Programming Language :: Python :: 3.7
Classifier: Programming Language :: Python :: 3.8
Classifier: Programming Language :: Python :: 3.9
Classifier: Topic :: Software Development :: Libraries :: Python Modules
Requires-Python: >=3.7
Requires-Dist: absl-py~=1.0
Requires-Dist: attrs<24,>=22
Requires-Dist: dm-tree~=0.1.8
Requires-Dist: mpmath~=1.2
Requires-Dist: numpy<3.0,>=1.21
Requires-Dist: scipy~=1.7
Dynamic: author
Dynamic: author-email
Dynamic: classifier
Dynamic: description
Dynamic: description-content-type
Dynamic: home-page
Dynamic: keywords
Dynamic: license
Dynamic: requires-dist
Dynamic: requires-python
Dynamic: summary
